pyscrabbler.py
pyscrabbler-1.1.2.data/data/Dictionary.txt
pyscrabbler-1.1.2.dist-info/METADATA
pyscrabbler-1.1.2.dist-info/WHEEL
pyscrabbler-1.1.2.dist-info/entry_points.txt
pyscrabbler-1.1.2.dist-info/top_level.txt
pyscrabbler-1.1.2.dist-info/RECORD
