Metadata-Version: 2.1
Name: pyscrabbler
Version: 1.1.2
Summary: Provide a set of letters and retrieve a list of potential words and point values for Scrabble.
Home-page: http://michaelwarmbier.com
Author: Michael Warmbier
Author-email: Michael Warmbier <business@michaelwarmbier.com>
Project-URL: Homepage, https://github.com/MichaelWarmbier/PyScrabbler
Keywords: scrabble,utility
